brython/__init__.py
brython/__main__.py
brython/list_modules.py
brython/make_file_system.py
brython/make_package.py
brython/python_minifier.py
brython/data/README.txt
brython/data/brython.js
brython/data/brython_stdlib.js
brython/data/demo.html
brython/data/index.html
brython/data/unicode.txt
brython-3.14.0.dist-info/METADATA
brython-3.14.0.dist-info/WHEEL
brython-3.14.0.dist-info/entry_points.txt
brython-3.14.0.dist-info/RECORD
