Metadata-Version: 2.4
Name: brython
Version: 3.14.0
Summary: Brython is an implementation of Python 3 running in the browser
Project-URL: Homepage, https://brython.info
Project-URL: Source, https://github.com/brython-dev/brython
Project-URL: Bug Tracker, https://github.com/brython-dev/brython/issues
Author-email: Pierre Quentel <pierre.quentel@gmail.com>
Classifier: License :: OSI Approved :: BSD License
Classifier: Operating System :: OS Independent
Classifier: Programming Language :: Python :: 3
Requires-Python: >=3.12
